[{"categories":null,"contents":"With an unwavering commitment to high-performance high-assurance software engineering, our founders Prof Karthikeyan Bhargavan, Dr Franziskus Kiefer, and Dr Jonathan Protzenko have a demonstrated track record of solving the most challenging problems. With a combined experience of over 40 years in the cryptography and formal methods space, the three co-founders are uniquely equipped to solve cryptographic challenges; starting from the design and analysis phase all the way to the production system.","date":"2022-01-03T00:00:00Z","permalink":"https://cryspen.github.io/about/","tags":["about-us","about-hugo","contact"],"title":"The Team"},{"categories":null,"contents":"HACL*: A Verified Modern Cryptographic Library. Jean Karim Zinzindohoué, Karthikeyan Bhargavan, Jonathan Protzenko, Benjamin Beurdouche. ACM Conference on Computer and Communications Security 2017: 1789-1806 Verified Models and Reference Implementations for the TLS 1.3 Standard Candidate. Karthikeyan Bhargavan, Bruno Blanchet, Nadim Kobeissi. IEEE Symposium on Security and Privacy 2017: 483-502 hacspec: Towards Verifiable Crypto Standards. Karthikeyan Bhargavan, Franziskus Kiefer, Pierre-Yves Strub. Security Standardisation Research 2018: 1-20 Formally Verified Cryptographic Web Applications in WebAssembly.","date":null,"permalink":"https://cryspen.github.io/publications/","tags":null,"title":""}]